[{"title":"mern","description":"full stack","price":"1299","id":0.8857678354461602},{"title":"DevOps","description":"Ci/cd,kubernetes and more","price":"1399","id":0.9686330724884409},{"title":"Al/ml","description":"Python and Deep Learning","price":"2000","id":0.4113485200647371},{"title":"Data Science","description":"R and Python","price":"3999","id":0.5771925512033242},{"title":"Front end Course","description":"React framework","price":"1000","id":0.7099690806575374},{"title":"new 1","description":"new 1","price":"1299","id":0.3743157033269364}]